crudapi/__init__.py
crudapi/api.py
crudapi/core/__init__.py
crudapi/core/config.py
crudapi/core/database.py
crudapi/core/dependencies.py
crudapi/core/exceptions.py
crudapi/core/logging.py
crudapi/core/openapi.py
crudapi/core/paginator.py
crudapi/core/types.py
crudapi/mixins/__init__.py
crudapi/mixins/base.py
crudapi/mixins/create.py
crudapi/mixins/delete.py
crudapi/mixins/search.py
crudapi/mixins/update.py
crudapi/models/__init__.py
crudapi/models/base.py
crudapi/models/update.py
crudapi/routers/__init__.py
crudapi/routers/create.py
crudapi/routers/delete.py
crudapi/routers/search.py
crudapi/routers/update.py
crudapi/services/__init__.py
crudapi/services/create.py
crudapi/services/delete.py
crudapi/services/search.py
crudapi/services/update.py
crudapi-0.5.0.dist-info/WHEEL
crudapi-0.5.0.dist-info/METADATA
crudapi-0.5.0.dist-info/RECORD
