Metadata-Version: 2.1
Name: crudapi
Version: 0.5.0
Summary: The easiest way to create your Restful CRUD APIs
Home-page: https://github.com/unmateo/crudapi
Author: Mateo Harfuch
Author-email: mharfuch@gmail.com
Requires-Python: >=3.9,<4.0
Classifier: Programming Language :: Python :: 3
Classifier: Programming Language :: Python :: 3.9
Requires-Dist: fastapi (>=0.68.1,<0.69.0)
Requires-Dist: sqlmodel (>=0.0.4,<0.0.5)
Project-URL: Documentation, https://github.com/unmateo/crudapi
Project-URL: Repository, https://github.com/unmateo/crudapi
